neosekai_api/__init__.py
neosekai_api/chapter.py
neosekai_api/constants.py
neosekai_api/helper.py
neosekai_api/novel.py
neosekai_api-2.1.0.dist-info/LICENSE
neosekai_api-2.1.0.dist-info/METADATA
neosekai_api-2.1.0.dist-info/WHEEL
neosekai_api-2.1.0.dist-info/top_level.txt
neosekai_api-2.1.0.dist-info/RECORD
